tree_sitter_gram/__init__.py
tree_sitter_gram/__init__.pyi
tree_sitter_gram/_binding.abi3.so
tree_sitter_gram/binding.c
tree_sitter_gram/py.typed
tree_sitter_gram/queries/highlights.scm
tree_sitter_gram-0.2.7.dist-info/METADATA
tree_sitter_gram-0.2.7.dist-info/WHEEL
tree_sitter_gram-0.2.7.dist-info/top_level.txt
tree_sitter_gram-0.2.7.dist-info/RECORD
tree_sitter_gram-0.2.7.dist-info/licenses/LICENSE
